crossfilt/identical_reads.py
crossfilt/liftover_bam.py
crossfilt/split_bam.py
crossfilt/lib/liftover_functions.py
crossfilt-0.2.1.dist-info/licenses/LICENSE
crossfilt-0.2.1.dist-info/METADATA
crossfilt-0.2.1.dist-info/WHEEL
crossfilt-0.2.1.dist-info/entry_points.txt
crossfilt-0.2.1.dist-info/top_level.txt
crossfilt-0.2.1.dist-info/RECORD
