Metadata-Version: 2.4
Name: crossfilt
Version: 0.2.1
Summary: Tools to filter reads causing alignment bias in cross-species genomic comparisons
Author-email: Kenneth A Barr <kenneth.a.barr@gmail.com>
License-Expression: GPL-3.0-or-later
Project-URL: Repository, https://github.com/kennethabarr/CrossFilt.git
Keywords: comparative genomics,primate genetics,alignment bias
Requires-Python: >=3.10
License-File: LICENSE
Requires-Dist: pysam
Requires-Dist: bx-python
Dynamic: license-file
